{"cameraMode":{"drawMode":0,"name":"Shaded","section":"Shading Mode"},"sceneLighting":false,"audioPlay":false,"sceneViewState":{"m_AlwaysRefresh":false,"showFog":true,"showSkybox":false,"showFlares":true,"showImageEffects":true,"showParticleSystems":true,"showVisualEffectGraphs":true,"m_FxEnabled":true},"in2DMode":false,"pivot":{"x":2.4014861583709719,"y":0.7329373359680176,"z":-0.3139392137527466},"rotation":{"x":0.019664589315652849,"y":0.7746928334236145,"z":0.024203011766076089,"w":-0.6316235661506653},"size":1.2247449159622193,"orthographic":false}